pytest_securestore
