Metadata-Version: 1.2
Name: pytest-securestore
Version: 0.1.1
Summary: An encrypted password store for use within pytest cases
Home-page: https://github.com/gregfitch/pytest-securestore
Author: Greg Fitch
Author-email: greg@openstax.org
Maintainer: Greg Fitch
Maintainer-email: greg@openstax.org
License: MIT
Platform: UNKNOWN
Classifier: Development Status :: 4 - Beta
Classifier: Framework :: Pytest
Classifier: Intended Audience :: Developers
Classifier: Topic :: Software Development :: Testing
Classifier: Programming Language :: Python
Classifier: Programming Language :: Python :: 3
Classifier: Programming Language :: Python :: 3.4
Classifier: Programming Language :: Python :: 3.5
Classifier: Programming Language :: Python :: 3.6
Classifier: Programming Language :: Python :: 3.7
Classifier: Programming Language :: Python :: Implementation :: CPython
Classifier: Programming Language :: Python :: Implementation :: PyPy
Classifier: Operating System :: OS Independent
Classifier: License :: OSI Approved :: MIT License
Requires-Python: !=3.0.*, !=3.1.*, !=3.2.*, !=3.3.*
